dockingFormatter.py
formatter.py
dockingFormatter-1.1.1.dist-info/LICENSE
dockingFormatter-1.1.1.dist-info/METADATA
dockingFormatter-1.1.1.dist-info/WHEEL
dockingFormatter-1.1.1.dist-info/entry_points.txt
dockingFormatter-1.1.1.dist-info/top_level.txt
dockingFormatter-1.1.1.dist-info/RECORD
