Metadata-Version: 2.1
Name: dockingFormatter
Version: 1.1.1
Summary: A docking logs formatter
Home-page: https://github.com/LSWarss/dockingFormatter
Author: Łukasz Stachnik
Author-email: ls.warss98@gmail.com
License: MIT License
Platform: UNKNOWN
Classifier: Programming Language :: Python :: 3
Classifier: License :: OSI Approved :: GNU General Public License v3 or later (GPLv3+)
Classifier: Operating System :: OS Independent
Requires-Dist: openpyxl
Requires-Dist: Click
Provides-Extra: dev
Requires-Dist: pytest (>=6.0) ; extra == 'dev'
